CAlab5/CAlab5.srcs/sources_1/new/fsm_counter.v
module fsm_counter (
    input        clk,
    input        rst,
    input  [3:0] sw_in,
    output reg [3:0] led_out,
    output reg   cnt_en
);

    localparam S0 = 1'b0,
               S1 = 1'b1;

    reg        state;
    reg  [3:0] counter;

    always @(posedge clk or posedge rst) begin
        if (rst) begin
            state   <= S0;
            counter <= 4'd0;
            led_out <= 4'd0;
            cnt_en  <= 1'b0;
        end
        else begin
            case (state)

                S0: begin
                    cnt_en  <= 1'b0;
                    led_out <= 4'd0;
                    if (sw_in != 4'd0) begin
                        counter <= sw_in;
                        state   <= S1;
                    end
                end

                S1: begin
                    cnt_en <= 1'b1;
                    if (counter == 4'd0) begin
                        cnt_en  <= 1'b0;
                        led_out <= 4'd0;
                        state   <= S0;
                    end
                    else begin
                        counter <= counter - 4'd1;
                        led_out <= counter - 4'd1;
                    end
                end

                default: state <= S0;

            endcase
        end
    end

endmodule

CAlab5/CAlab5.srcs/sim_1/new/task2TB.v
`timescale 1ns / 1ps
//////////////////////////////////////////////////////////////////////////////////
// Company: 
// Engineer: 
// 
// Create Date: 02/19/2026 11:18:21 AM
// Design Name: 
// Module Name: task2TB
// Project Name: 
// Target Devices: 
// Tool Versions: 
// Description: 
// 
// Dependencies: 
// 
// Revision:
// Revision 0.01 - File Created
// Additional Comments:
// 
//////////////////////////////////////////////////////////////////////////////////


module tb_fsm_counter;

    reg        clk;
    reg        rst;
    reg  [3:0] sw_in;
    wire [3:0] led_out;
    wire       cnt_en;

    fsm_counter uut (
        .clk    (clk),
        .rst    (rst),
        .sw_in  (sw_in),
        .led_out(led_out),
        .cnt_en (cnt_en)
    );

    always #5 clk = ~clk;

    initial begin
        clk   = 0;
        rst   = 0;
        sw_in = 4'd0;

        // Test 1: Reset
        rst = 1;
        @(posedge clk); #1;
        @(posedge clk); #1;
        rst = 0;
        $display("T1 RESET   | state=%b cnt_en=%b led_out=%d | expect state=0 cnt_en=0 led=0",
                  uut.state, cnt_en, led_out);

        // Test 2: sw_in=0, stay in S0
        sw_in = 4'd0;
        repeat(3) @(posedge clk); #1;
        $display("T2 SW=0    | state=%b cnt_en=%b led_out=%d | expect state=0 cnt_en=0 led=0",
                  uut.state, cnt_en, led_out);

        // Test 3: sw_in=5, enter S1 and count down
        sw_in = 4'd5;
        @(posedge clk); #1;
        sw_in = 4'd0;
        $display("T3 SW=5 S1 | state=%b cnt_en=%b led_out=%d | expect state=1 cnt_en=1",
                  uut.state, cnt_en, led_out);
        repeat(5) begin
            @(posedge clk); #1;
            $display("   COUNT   | state=%b cnt_en=%b led_out=%d counter=%d",
                      uut.state, cnt_en, led_out, uut.counter);
        end
        $display("T3 DONE    | state=%b cnt_en=%b led_out=%d | expect state=0 cnt_en=0 led=0",
                  uut.state, cnt_en, led_out);

        // Test 4: async reset mid-countdown
        sw_in = 4'd7;
        @(posedge clk); #1;
        sw_in = 4'd0;
        repeat(3) @(posedge clk); #1;
        $display("T4 PRE-RST | state=%b cnt_en=%b led_out=%d counter=%d",
                  uut.state, cnt_en, led_out, uut.counter);
        rst = 1; #3;
        $display("T4 MID-RST | state=%b cnt_en=%b led_out=%d | expect state=0 cnt_en=0 led=0",
                  uut.state, cnt_en, led_out);
        rst = 0;
        @(posedge clk); #1;

        // Test 5: sw_in=15, full countdown
        sw_in = 4'd15;
        @(posedge clk); #1;
        sw_in = 4'd0;
        $display("T5 SW=15   | state=%b cnt_en=%b | expect state=1 cnt_en=1",
                  uut.state, cnt_en);
        repeat(16) @(posedge clk); #1;
        $display("T5 DONE    | state=%b cnt_en=%b led_out=%d | expect state=0 cnt_en=0 led=0",
                  uut.state, cnt_en, led_out);

        $display("\nSimulation complete.");
        $finish;
    end

    initial begin
        $dumpfile("tb_fsm_counter.vcd");
        $dumpvars(0, tb_fsm_counter);
    end

endmodule

CAlab5/CAlab5.sim/sim_1/behav/xsim/tb_fsm_counter.vcd
$date
   Fri Feb 20 19:44:36 2026
$end
$version
  2020.1
$end
$timescale
  1ps
$end
$scope module tb_fsm_counter $end
$var reg 1 ! clk $end
$var reg 1 " rst $end
$var reg 4 # sw_in [3:0] $end
$var wire 4 $ led_out [3:0] $end
$var wire 1 % cnt_en $end
$scope module uut $end
$var wire 1 & clk $end
$var wire 1 ' rst $end
$var wire 4 ( sw_in [3:0] $end
$var reg 4 ) led_out [3:0] $end
$var reg 1 * cnt_en $end
$var reg 1 + state $end
$var reg 4 , counter [3:0] $end
$var parameter 0 - S0 $end
$var parameter 0 . S1 $end
$upscope $end
$upscope $end
$enddefinitions $end
#0
$dumpvars
0!
1"
b0 #
b0 $
0%
0&
1'
b0 (
b0 )
0*
0+
b0 ,
0-
1.
$end
#5000
1!
1&
#10000
0!
0&
#15000
1!
1&
#16000
0"
b0 #
0'
#20000
0!
0&
#25000
1!
1&
#30000
0!
0&
#35000
1!
1&
#40000
0!
0&
#45000
1!
1&
#46000
b101 #
b101 (
#50000
0!
0&
#55000
1!
1&
1+
b101 ,
#56000
b0 #
b0 (
#60000
0!
0&
#65000
1!
b100 $
1%
1&
b100 )
1*
b100 ,
#70000
0!
0&
#75000
1!
b11 $
1&
b11 )
b11 ,
#80000
0!
0&
#85000
1!
b10 $
1&
b10 )
b10 ,
#90000
0!
0&
#95000
1!
b1 $
1&
b1 )
b1 ,
#100000
0!
0&
#105000
1!
b0 $
1&
b0 )
b0 ,
#106000
b111 #
b111 (
#110000
0!
0&
#115000
1!
0%
1&
0*
0+
#116000
b0 #
b0 (
#120000
0!
0&
#125000
1!
1&
#130000
0!
0&
#135000
1!
1&
#140000
0!
0&
#145000
1!
1&
#146000
1"
1'
#149000
0"
0'
#150000
0!
0&
#155000
1!
1&
#156000
b1111 #
b1111 (
#160000
0!
0&
#165000
1!
1&
1+
b1111 ,
#166000
b0 #
b0 (
#170000
0!
0&
#175000
1!
b1110 $
1%
1&
b1110 )
1*
b1110 ,
#180000
0!
0&
#185000
1!
b1101 $
1&
b1101 )
b1101 ,
#190000
0!
0&
#195000
1!
b1100 $
1&
b1100 )
b1100 ,
#200000
0!
0&
#205000
1!
b1011 $
1&
b1011 )
b1011 ,
#210000
0!
0&
#215000
1!
b1010 $
1&
b1010 )
b1010 ,
#220000
0!
0&
#225000
1!
b1001 $
1&
b1001 )
b1001 ,
#230000
0!
0&
#235000
1!
b1000 $
1&
b1000 )
b1000 ,
#240000
0!
0&
#245000
1!
b111 $
1&
b111 )
b111 ,
#250000
0!
0&
#255000
1!
b110 $
1&
b110 )
b110 ,
#260000
0!
0&
#265000
1!
b101 $
1&
b101 )
b101 ,
#270000
0!
0&
#275000
1!
b100 $
1&
b100 )
b100 ,
#280000
0!
0&
#285000
1!
b11 $
1&
b11 )
b11 ,
#290000
0!
0&
#295000
1!
b10 $
1&
b10 )
b10 ,
#300000
0!
0&
#305000
1!
b1 $
1&
b1 )
b1 ,
#310000
0!
0&
#315000
1!
b0 $
1&
b0 )
b0 ,
#320000
0!
0&
#325000
1!
0%
1&
0*
0+
